calculator/__init__.py
calculator/calculator.py
m1nx4s_calculator-1.2.0.dist-info/LICENSE
m1nx4s_calculator-1.2.0.dist-info/METADATA
m1nx4s_calculator-1.2.0.dist-info/WHEEL
m1nx4s_calculator-1.2.0.dist-info/top_level.txt
m1nx4s_calculator-1.2.0.dist-info/RECORD
