Metadata-Version: 2.1
Name: m1nx4s-calculator
Version: 1.2.0
Summary: my first calculator package
Home-page: https://github.com/m1nx4s/calculator
Author: Mindaugas Kancevicius
Keywords: development,setup,setuptools
Requires-Python: >=3.10, <4
License-File: LICENSE
